[
  {
    "title": "Facebook to tag ‘harmful’ posts as boycott widens",
    "summary": "The firm has been under pressure to improve its moderation of the content on its platform.",
    "tag": "Business"
  },
  {
    "title": "Justin Bieber files defamation lawsuit after assault claims",
    "summary": "Two anonymous Twitter accounts made sexual assault allegations against the singer last week.",
    "tag": "US \u0026 Canada"
  },
  {
    "title": "How Vietnam saved a British patient and kept a clean sheet",
    "summary": "Stephen Cameron spent 68 days on a ventilator, but beat the odds to survive coronavirus.",
    "tag": "News"
  }
]

